<annotation>
	<folder>images</folder>
	<filename>waste_class_192.jpg</filename>
	<path>/home/bokuto/Documents/Capstone/wasteClassification/data/images/waste_class_192.jpg</path>
	<source>
		<database>Unknown</database>
	</source>
	<size>
		<width>512</width>
		<height>384</height>
		<depth>3</depth>
	</size>
	<segmented>0</segmented>
	<object>
		<name>metal</name>
		<pose>Unspecified</pose>
		<truncated>0</truncated>
		<difficult>0</difficult>
		<bndbox>
			<xmin>4</xmin>
			<ymin>64</ymin>
			<xmax>48</xmax>
			<ymax>136</ymax>
		</bndbox>
	</object>
	<object>
		<name>trash</name>
		<pose>Unspecified</pose>
		<truncated>1</truncated>
		<difficult>0</difficult>
		<bndbox>
			<xmin>1</xmin>
			<ymin>135</ymin>
			<xmax>19</xmax>
			<ymax>262</ymax>
		</bndbox>
	</object>
	<object>
		<name>cardboard</name>
		<pose>Unspecified</pose>
		<truncated>1</truncated>
		<difficult>0</difficult>
		<bndbox>
			<xmin>17</xmin>
			<ymin>232</ymin>
			<xmax>126</xmax>
			<ymax>384</ymax>
		</bndbox>
	</object>
	<object>
		<name>plastic</name>
		<pose>Unspecified</pose>
		<truncated>1</truncated>
		<difficult>0</difficult>
		<bndbox>
			<xmin>145</xmin>
			<ymin>196</ymin>
			<xmax>407</xmax>
			<ymax>384</ymax>
		</bndbox>
	</object>
	<object>
		<name>plastic</name>
		<pose>Unspecified</pose>
		<truncated>1</truncated>
		<difficult>0</difficult>
		<bndbox>
			<xmin>76</xmin>
			<ymin>1</ymin>
			<xmax>254</xmax>
			<ymax>286</ymax>
		</bndbox>
	</object>
	<object>
		<name>plastic</name>
		<pose>Unspecified</pose>
		<truncated>1</truncated>
		<difficult>0</difficult>
		<bndbox>
			<xmin>267</xmin>
			<ymin>1</ymin>
			<xmax>505</xmax>
			<ymax>302</ymax>
		</bndbox>
	</object>
</annotation>
